README.rst
setup.cfg
setup.py
src/codeviking.random.egg-info/PKG-INFO
src/codeviking.random.egg-info/SOURCES.txt
src/codeviking.random.egg-info/dependency_links.txt
src/codeviking.random.egg-info/top_level.txt
src/codeviking/random/__init__.py
src/codeviking/random/_version.py
src/codeviking/random/collection.py
src/codeviking/random/lcg.py
src/codeviking/random/primitive.py
src/codeviking/random/rng.py
test/test_collection.py
test/test_random.py
test/test_stats.py