Metadata-Version: 2.1
Name: codeviking.random
Version: 0.15.2
Summary: Cross-language random number generators with many useful random number generation methods.
Home-page: https://bitbucket.org/codeviking/python-codeviking.random/
Author: Dan Bullok
Author-email: opensource@codeviking.com
License: ISC
Platform: any
Classifier: Development Status :: 4 - Beta
Classifier: Intended Audience :: Developers
Classifier: License :: OSI Approved
Classifier: License :: OSI Approved :: ISC License (ISCL)
Classifier: Natural Language :: English
Classifier: Operating System :: OS Independent
Classifier: Programming Language :: Python
Classifier: Programming Language :: Python :: 3
Classifier: Programming Language :: Python :: 3 :: Only
Classifier: Topic :: Software Development :: Libraries :: Python Modules
Classifier: Topic :: Scientific/Engineering :: Mathematics
